nbjoint.py
nbjoint-0.14a1.dist-info/LICENSE
nbjoint-0.14a1.dist-info/METADATA
nbjoint-0.14a1.dist-info/WHEEL
nbjoint-0.14a1.dist-info/top_level.txt
nbjoint-0.14a1.dist-info/RECORD
