Metadata-Version: 2.1
Name: nbjoint
Version: 0.14a1
Summary: Generates a navigable book-like structure         to a collection of jupyter notebooks
Home-page: https://github.com/rmsrosa/nbjoint
Author: Ricardo M. S. Rosa
Author-email: rmsrosa@gmail.com
License: UNKNOWN
Project-URL: Documentation, https://nbjoint.readthedocs.io/
Project-URL: Source Code, https://github.com/rmsrosa/nbjoint
Platform: UNKNOWN
Classifier: Programming Language :: Python :: 3.5
Classifier: Programming Language :: Python :: 3.6
Classifier: Programming Language :: Python :: 3.7
Classifier: Programming Language :: Python :: 3.8
Classifier: Development Status :: 3 - Alpha
Classifier: Framework :: Jupyter
Classifier: Operating System :: MacOS
Classifier: Operating System :: POSIX :: Linux
Classifier: License :: OSI Approved :: MIT License
Requires-Python: >=3.5
